{
  "author": {
    "id": "t2_70d8x",
    "name": "blueteamwins"
  },
  "date": {
    "day": 1375056000,
    "full": 1375120071,
    "month": 1372636800,
    "week": 1374969600
  },
  "id": "t3_1jafhg",
  "misc": {
    "postHint": "image"
  },
  "picture": {
    "full": "https://external-preview.redd.it/cOWbJdpxjGvRlxjPvkZ4bi7ZPhxIn65fJsaBvJKxkMk.jpg?auto=webp&s=59752c4d372f29361aa16df0d162853e28a42340",
    "preview": "https://external-preview.redd.it/cOWbJdpxjGvRlxjPvkZ4bi7ZPhxIn65fJsaBvJKxkMk.jpg?width=640&crop=smart&auto=webp&s=380418f38b516e8c0e4e912bf0d75bc1d41f0991",
    "thumbnail": "https://b.thumbs.redditmedia.com/kpI2HHOnGArfusiGO_5t53HH30BbEx8J7p5VkOaHLTo.jpg"
  },
  "score": {
    "comments": 5,
    "downs": 0,
    "ratio": 0.79,
    "ups": 39,
    "value": 39
  },
  "subreddit": {
    "id": "t5_2sbq3",
    "name": "EarthPorn"
  },
  "tags": [],
  "title": "Scarp Ridge, Colorado",
  "url": "https://www.reddit.com/r/EarthPorn/comments/1jafhg/scarp_ridge_colorado_oc_3264x2488/"
}
