{
  "author": {
    "id": "t2_chtcz",
    "name": "d230"
  },
  "date": {
    "day": 1374710400,
    "full": 1374727573,
    "month": 1372636800,
    "week": 1374364800
  },
  "id": "t3_1j0bfu",
  "misc": {
    "postHint": "link"
  },
  "picture": {
    "full": "https://external-preview.redd.it/P_Br4AJgC-UY5yMMq7U9oBL08n5BQdqDlHOAyai469Q.jpg?auto=webp&s=121881b73f75f43c4d5e41c87f3d800ffb460fdd",
    "preview": "https://external-preview.redd.it/P_Br4AJgC-UY5yMMq7U9oBL08n5BQdqDlHOAyai469Q.jpg?width=640&crop=smart&auto=webp&s=943b75a1cbc0c3782fe8aad6040fe365e0bb3846",
    "thumbnail": "https://b.thumbs.redditmedia.com/m6XhiWPCV0p_mWzZuU4Rp3BP-8pBf5uDBvUAAWASn-I.jpg"
  },
  "score": {
    "comments": 0,
    "downs": 0,
    "ratio": 0.71,
    "ups": 11,
    "value": 11
  },
  "subreddit": {
    "id": "t5_2sbq3",
    "name": "EarthPorn"
  },
  "tags": [],
  "title": "The calm shores of Chicago",
  "url": "https://www.reddit.com/r/EarthPorn/comments/1j0bfu/the_calm_shores_of_chicago_4272x2848/"
}
