{
  "author": {
    "id": "t2_amsw1",
    "name": "Tuttle_not_Buttle"
  },
  "date": {
    "day": 1481328000,
    "full": 1481376011,
    "month": 1480550400,
    "week": 1480809600
  },
  "id": "t3_5hk33g",
  "misc": {
    "postHint": "image"
  },
  "picture": {
    "full": "https://external-preview.redd.it/Ku615mo_GtPlzwezshZgbCg7ZnMZJl31QgL6vvEmY68.jpg?auto=webp&s=a7e61a2513b025aac136f098d1115272bfb35b13",
    "preview": "https://external-preview.redd.it/Ku615mo_GtPlzwezshZgbCg7ZnMZJl31QgL6vvEmY68.jpg?width=640&crop=smart&auto=webp&s=003b9c287f918ccbb516b24d745fc7ebf5cc2625",
    "thumbnail": "https://b.thumbs.redditmedia.com/Kyz7nS0WuJU0kndpdF0KrUxukDvHt1mIbynsN0sj7yI.jpg"
  },
  "score": {
    "comments": 37,
    "downs": 0,
    "ratio": 0.96,
    "ups": 6222,
    "value": 6222
  },
  "subreddit": {
    "id": "t5_2sbq3",
    "name": "EarthPorn"
  },
  "tags": [],
  "title": "Last days of Autumn, Castlerigg, the Lake District",
  "url": "https://www.reddit.com/r/EarthPorn/comments/5hk33g/last_days_of_autumn_castlerigg_the_lake_district/"
}
