{
  "author": {
    "id": "t2_to7y8",
    "name": "BrandonRossV"
  },
  "date": {
    "day": 1527724800,
    "full": 1527806030,
    "month": 1525132800,
    "week": 1527379200
  },
  "id": "t3_8nmpz9",
  "misc": {
    "postHint": "image"
  },
  "picture": {
    "full": "https://preview.redd.it/i6lacsn7q9111.jpg?auto=webp&s=ec9d2cd7b81686749ae7279d88b180b667a1558e",
    "preview": "https://preview.redd.it/i6lacsn7q9111.jpg?width=640&crop=smart&auto=webp&s=2bc5a4882507ce26fdf5659bc6afa0c5e7afffea",
    "thumbnail": "https://b.thumbs.redditmedia.com/i00RXaaWMkb8xb_l1NAc6kAGjupVeplwaHhcF85i92c.jpg"
  },
  "score": {
    "comments": 0,
    "downs": 0,
    "ratio": 0.92,
    "ups": 33,
    "value": 33
  },
  "subreddit": {
    "id": "t5_2sbq3",
    "name": "EarthPorn"
  },
  "tags": [],
  "title": "Horseshoe Bay, Bermuda 🇧🇲 (OC)",
  "url": "https://www.reddit.com/r/EarthPorn/comments/8nmpz9/horseshoe_bay_bermuda_oc3024x4032/"
}
