{
  "author": {
    "id": "t2_f2guy",
    "name": "RobDickinson"
  },
  "date": {
    "day": 1526515200,
    "full": 1526531123,
    "month": 1525132800,
    "week": 1526169600
  },
  "id": "t3_8k1efj",
  "misc": {
    "postHint": "link"
  },
  "picture": {
    "full": "https://external-preview.redd.it/L-zARzw67nraiK0qMgf1zBK9Wd5fCARkDhYo1eF15nI.jpg?auto=webp&s=fb7230acd64d45d1b5a6dec8027832a7f34f1aee",
    "preview": "https://external-preview.redd.it/L-zARzw67nraiK0qMgf1zBK9Wd5fCARkDhYo1eF15nI.jpg?width=640&crop=smart&auto=webp&s=5cbe799632cf93c6ff892ed18f994a0669122baa",
    "thumbnail": "https://b.thumbs.redditmedia.com/3qfclYnpfP5sUl6Rhbb3YhfaqtTECnp-XDJaoisOI7E.jpg"
  },
  "score": {
    "comments": 8,
    "downs": 0,
    "ratio": 0.97,
    "ups": 612,
    "value": 612
  },
  "subreddit": {
    "id": "t5_2sbq3",
    "name": "EarthPorn"
  },
  "tags": [],
  "title": "How Does it Feel? Stars over Lake Heron, NZ",
  "url": "https://www.reddit.com/r/EarthPorn/comments/8k1efj/how_does_it_feel_stars_over_lake_heron_nz/"
}
