{
  "author": {
    "id": "t2_8g3yz",
    "name": "AndersHigh"
  },
  "date": {
    "day": 1425081600,
    "full": 1425147540,
    "month": 1422748800,
    "week": 1424563200
  },
  "id": "t3_2xhb9o",
  "misc": {
    "postHint": "link"
  },
  "picture": {
    "full": "https://external-preview.redd.it/2Xct7ZYhfi7WAGiHJ3tii73awpB5nI8cXByLe_eT8wo.jpg?auto=webp&s=51c65c639d837ba289acf290d02ee8f5029e3479",
    "preview": "https://external-preview.redd.it/2Xct7ZYhfi7WAGiHJ3tii73awpB5nI8cXByLe_eT8wo.jpg?width=640&crop=smart&auto=webp&s=f4ce792e9d87a758b6929ab2705a6f3b652f0f90",
    "thumbnail": "https://a.thumbs.redditmedia.com/KPCAO3yr6yOT2H1L_N9ggF1Jk8FY_Wngz2wRw_hQQr4.jpg"
  },
  "score": {
    "comments": 0,
    "downs": 0,
    "ratio": 0.85,
    "ups": 13,
    "value": 13
  },
  "subreddit": {
    "id": "t5_2sbq3",
    "name": "EarthPorn"
  },
  "tags": [],
  "title": "Sunset in the Pai canyons, Thailand",
  "url": "https://www.reddit.com/r/EarthPorn/comments/2xhb9o/sunset_in_the_pai_canyons_thailand_4733x2687_oc/"
}
