{
  "author": {
    "id": "t2_68cwum0g",
    "name": "Average_Zer0"
  },
  "date": {
    "day": 1621209600,
    "full": 1621218100,
    "month": 1619827200,
    "week": 1621123200
  },
  "id": "t3_ne4a89",
  "misc": {
    "postHint": "image"
  },
  "picture": {
    "full": "https://preview.redd.it/vtf8vp9cblz61.jpg?auto=webp&s=ef9df74ba98716e5fa2d6829478b5e77f35c0763",
    "preview": "https://preview.redd.it/vtf8vp9cblz61.jpg?width=640&crop=smart&auto=webp&s=d7b1f62e4af5d332a452c9417da77a043f29c78e",
    "thumbnail": "https://a.thumbs.redditmedia.com/lroKSsH9pKBfFmnw6bBpGbembvPCtqU_zBYnA0Ge724.jpg"
  },
  "score": {
    "comments": 2,
    "downs": 0,
    "ratio": 0.89,
    "ups": 19,
    "value": 19
  },
  "subreddit": {
    "id": "t5_2sbq3",
    "name": "EarthPorn"
  },
  "tags": [],
  "title": "Dead pine forest in Yellowstone National Park, WY",
  "url": "https://www.reddit.com/r/EarthPorn/comments/ne4a89/dead_pine_forest_in_yellowstone_national_park_wy/"
}
