{
  "author": {
    "id": "t2_3qypz",
    "name": "baronyuan"
  },
  "date": {
    "day": 1517875200,
    "full": 1517912783,
    "month": 1517443200,
    "week": 1517702400
  },
  "id": "t3_7vmgtr",
  "misc": {
    "postHint": "image"
  },
  "picture": {
    "full": "https://preview.redd.it/19r5a0ncjke01.jpg?auto=webp&s=985c6b4c9cebdcc0806a9f4973a8dc4555274597",
    "preview": "https://preview.redd.it/19r5a0ncjke01.jpg?width=640&crop=smart&auto=webp&s=6c2f6a866780a9b4f752f5f2436d0e94dd73555a",
    "thumbnail": "https://b.thumbs.redditmedia.com/4xoj2u8f2w3Mj14C7z8kZb9ZlyAPY00h4dlqtYdDOUY.jpg"
  },
  "score": {
    "comments": 14,
    "downs": 0,
    "ratio": 0.97,
    "ups": 200,
    "value": 200
  },
  "subreddit": {
    "id": "t5_2sbq3",
    "name": "EarthPorn"
  },
  "tags": [],
  "title": "I had no idea the sun was available in Oregon.  IG:@thirty6chambers",
  "url": "https://www.reddit.com/r/EarthPorn/comments/7vmgtr/i_had_no_idea_the_sun_was_available_in_oregon/"
}
