{
  "author": {
    "id": "t2_59s62",
    "name": "winningelephant"
  },
  "date": {
    "day": 1519344000,
    "full": 1519413861,
    "month": 1517443200,
    "week": 1518912000
  },
  "id": "t3_7zqoki",
  "misc": {
    "postHint": "image"
  },
  "picture": {
    "full": "https://preview.redd.it/7l5qx3ufj0i01.jpg?auto=webp&s=2335ce2a8c47c173d6d12edc0c9655e2bb958e66",
    "preview": "https://preview.redd.it/7l5qx3ufj0i01.jpg?width=640&crop=smart&auto=webp&s=11a96fa784313bf486f8344727b1866781b2252e",
    "thumbnail": "https://b.thumbs.redditmedia.com/lMdP54bcKQwB7gK44KJaXEMGsCTJOb3bf_KzU0l9b4A.jpg"
  },
  "score": {
    "comments": 1,
    "downs": 0,
    "ratio": 0.86,
    "ups": 56,
    "value": 56
  },
  "subreddit": {
    "id": "t5_2sbq3",
    "name": "EarthPorn"
  },
  "tags": [],
  "title": "Middle Earth or Glacier National Park, Montana in early August?",
  "url": "https://www.reddit.com/r/EarthPorn/comments/7zqoki/middle_earth_or_glacier_national_park_montana_in/"
}
