{
  "author": {
    "id": "t2_j5bjg",
    "name": "badboidurryking"
  },
  "date": {
    "day": 1449446400,
    "full": 1449474091,
    "month": 1448928000,
    "week": 1449360000
  },
  "id": "t3_3vrl8l",
  "misc": {
    "postHint": "image"
  },
  "picture": {
    "full": "https://external-preview.redd.it/ICPYzVSayHO07_YQp1pS-8BlDttbZksguDW-V5FSzTk.jpg?auto=webp&s=8d3985747310d0ff624a95089676bdf12b01ae3b",
    "preview": "https://external-preview.redd.it/ICPYzVSayHO07_YQp1pS-8BlDttbZksguDW-V5FSzTk.jpg?width=640&crop=smart&auto=webp&s=15e9485259953b1e4eab977fd06d984d8ea7bb26",
    "thumbnail": "https://b.thumbs.redditmedia.com/ebWXP9GpgJZWXbaMqqCDKGpeiHZvPvQvh000cgWG5xc.jpg"
  },
  "score": {
    "comments": 0,
    "downs": 0,
    "ratio": 0.89,
    "ups": 7,
    "value": 7
  },
  "subreddit": {
    "id": "t5_2sbq3",
    "name": "EarthPorn"
  },
  "tags": [],
  "title": "Southwest National Park, Tasmania Australia by Matt Glastonbury",
  "url": "https://www.reddit.com/r/EarthPorn/comments/3vrl8l/southwest_national_park_tasmania_australia_by/"
}
