{
  "author": {
    "id": "t2_6whpu",
    "name": "sonalis1092"
  },
  "date": {
    "day": 1349568000,
    "full": 1349581579,
    "month": 1349049600,
    "week": 1349568000
  },
  "id": "t3_112o8q",
  "misc": {
    "postHint": "image"
  },
  "picture": {
    "full": "https://external-preview.redd.it/9s249qzLxnE-698lFkRSrqiX1l6Bh0m2lix-JwIzmXA.jpg?auto=webp&s=bd7ee54b0257f403a875e7465adc3ec8a475d1e3",
    "preview": "https://external-preview.redd.it/9s249qzLxnE-698lFkRSrqiX1l6Bh0m2lix-JwIzmXA.jpg?width=640&crop=smart&auto=webp&s=1073de76198407ebc7113fb33a8407652a6fafa1",
    "thumbnail": "https://b.thumbs.redditmedia.com/Ej0iOTpfW0ufYD0GYocp286RxyhpfA0aZ2PXd0U8alg.jpg"
  },
  "score": {
    "comments": 2,
    "downs": 0,
    "ratio": 0.88,
    "ups": 53,
    "value": 53
  },
  "subreddit": {
    "id": "t5_2sbq3",
    "name": "EarthPorn"
  },
  "tags": [],
  "title": "Sunrise on an old battlefield in Fredericksburg, VA, USA",
  "url": "https://www.reddit.com/r/EarthPorn/comments/112o8q/sunrise_on_an_old_battlefield_in_fredericksburg/"
}
