{
  "author": {
    "name": "[deleted]"
  },
  "date": {
    "day": 1575936000,
    "full": 1575938986,
    "month": 1575158400,
    "week": 1575763200
  },
  "id": "t3_e8j144",
  "misc": {
    "postHint": "image"
  },
  "picture": {
    "full": "https://preview.redd.it/3tl18ux2dp341.jpg?auto=webp&s=b06c7b281e1f9115575190fa2d48cca3e00da0c1",
    "preview": "https://preview.redd.it/3tl18ux2dp341.jpg?width=640&crop=smart&auto=webp&s=4d38b425e7c70156071f7ccc10c2f399c6817a57",
    "thumbnail": "https://b.thumbs.redditmedia.com/8vkfde63ftXrq7EMoWfWDWD_-KrVpCRWLM0Kp4ihF_E.jpg"
  },
  "score": {
    "comments": 1,
    "downs": 0,
    "ratio": 0.82,
    "ups": 15,
    "value": 15
  },
  "subreddit": {
    "id": "t5_2sbq3",
    "name": "EarthPorn"
  },
  "tags": [],
  "title": "Spring Mountains Southern Nevada USA (OC)",
  "url": "https://www.reddit.com/r/EarthPorn/comments/e8j144/spring_mountains_southern_nevada_usa_oc_1706_x_960/"
}
