{
  "author": {
    "id": "t2_3g15q",
    "name": "zathan"
  },
  "date": {
    "day": 1358035200,
    "full": 1358112277,
    "month": 1356998400,
    "week": 1358035200
  },
  "id": "t3_16idwl",
  "misc": {
    "postHint": "link"
  },
  "picture": {
    "full": "https://external-preview.redd.it/jjZEKdAfgLC97SjEDk_Itl4JXWXbBjeTuRT49889UAo.jpg?auto=webp&s=f1ae90f57c2f17fef2ab1644a8f928fb5082a71c",
    "preview": "https://external-preview.redd.it/jjZEKdAfgLC97SjEDk_Itl4JXWXbBjeTuRT49889UAo.jpg?width=640&crop=smart&auto=webp&s=28bd380996ba1ee1df1bba4f7bd1d2376a197f9b",
    "thumbnail": "https://b.thumbs.redditmedia.com/m9IuDPon_0K-6jYLjjdeEMP618_84sUmQepAGyUxiNY.jpg"
  },
  "score": {
    "comments": 0,
    "downs": 0,
    "ratio": 0.93,
    "ups": 13,
    "value": 13
  },
  "subreddit": {
    "id": "t5_2sbq3",
    "name": "EarthPorn"
  },
  "tags": [],
  "title": "Hong Island lagoon, Krabi, Thailand",
  "url": "https://www.reddit.com/r/EarthPorn/comments/16idwl/hong_island_lagoon_krabi_thailand_oc_1600_x_1056/"
}
