{
  "author": {
    "id": "t2_bn6ng",
    "name": "Continuent"
  },
  "date": {
    "day": 1453766400,
    "full": 1453807152,
    "month": 1451606400,
    "week": 1453593600
  },
  "id": "t3_42r2ij",
  "misc": {
    "postHint": "image"
  },
  "picture": {
    "full": "https://external-preview.redd.it/3jgQ2r4pKh3qqbmfCZT6Kf4xqIZYT6cvnWVYu4I1Q10.jpg?auto=webp&s=4bf6fb65a62fd311b1557491d73e8f42266832f5",
    "preview": "https://external-preview.redd.it/3jgQ2r4pKh3qqbmfCZT6Kf4xqIZYT6cvnWVYu4I1Q10.jpg?width=640&crop=smart&auto=webp&s=373936735f65d2a5ced7af3eb3efa610c34d1ce2",
    "thumbnail": "https://b.thumbs.redditmedia.com/5Q5Ntdont3azTIkI1JvckZlJe1twjzEtjAVCbcGVXag.jpg"
  },
  "score": {
    "comments": 1,
    "downs": 0,
    "ratio": 0.86,
    "ups": 10,
    "value": 10
  },
  "subreddit": {
    "id": "t5_2sbq3",
    "name": "EarthPorn"
  },
  "tags": [],
  "title": "Mount Toubkal Base camp (4160 x 2340)",
  "url": "https://www.reddit.com/r/EarthPorn/comments/42r2ij/mount_toubkal_base_camp_4160_x_2340/"
}
