{
  "author": {
    "id": "t2_h98kt",
    "name": "BurgerBuoy"
  },
  "date": {
    "day": 1418256000,
    "full": 1418308270,
    "month": 1417392000,
    "week": 1417910400
  },
  "id": "t3_2oz362",
  "misc": {
    "postHint": "image"
  },
  "picture": {
    "full": "https://external-preview.redd.it/SFlnDDYs8PaGtwLoxGc3qOO00jHloPfpPozYaJ034vw.jpg?auto=webp&s=336e5c14f6368189f35781328c5bd2b5edea148a",
    "preview": "https://external-preview.redd.it/SFlnDDYs8PaGtwLoxGc3qOO00jHloPfpPozYaJ034vw.jpg?width=640&crop=smart&auto=webp&s=cbc5211c7e275b3df90f465187deb44d1ec3858d",
    "thumbnail": "https://b.thumbs.redditmedia.com/FfcrcBlAJWUIT6C_e66agS-FqXiNv9D943kbmhNHGGM.jpg"
  },
  "score": {
    "comments": 4,
    "downs": 0,
    "ratio": 0.88,
    "ups": 68,
    "value": 68
  },
  "subreddit": {
    "id": "t5_2sbq3",
    "name": "EarthPorn"
  },
  "tags": [],
  "title": "Khamar-Daban Mountain Range, Siberia | By Alexandr Sudarchikov",
  "url": "https://www.reddit.com/r/EarthPorn/comments/2oz362/khamardaban_mountain_range_siberia_by_alexandr/"
}
