{
  "author": {
    "id": "t2_olcyc",
    "name": "KNO56"
  },
  "date": {
    "day": 1502841600,
    "full": 1502857900,
    "month": 1501545600,
    "week": 1502582400
  },
  "id": "t3_6tzqbf",
  "misc": {
    "postHint": "image"
  },
  "picture": {
    "full": "https://external-preview.redd.it/laAEK97wQ7l_vWcQRdsiigMsDwOQ38eCn1wvpDpSgIE.jpg?auto=webp&s=d8de1c1fc38115c84ada78dbce386c50d070ec53",
    "preview": "https://external-preview.redd.it/laAEK97wQ7l_vWcQRdsiigMsDwOQ38eCn1wvpDpSgIE.jpg?width=640&crop=smart&auto=webp&s=7f6bce85924aeef08e18828c284fb927c050ef15",
    "thumbnail": "https://b.thumbs.redditmedia.com/3eA3CZ5Kvv0JUtQuqPW_fZLw4S0oZW-b_1Bi06sAAzs.jpg"
  },
  "score": {
    "comments": 1,
    "downs": 0,
    "ratio": 0.86,
    "ups": 10,
    "value": 10
  },
  "subreddit": {
    "id": "t5_2sbq3",
    "name": "EarthPorn"
  },
  "tags": [],
  "title": "Iguazú waterfalls (Argentinian side) -",
  "url": "https://www.reddit.com/r/EarthPorn/comments/6tzqbf/iguazú_waterfalls_argentinian_side_40322268_oc/"
}
