{
  "author": {
    "id": "t2_5yq70al",
    "name": "Lordbingston"
  },
  "date": {
    "day": 1502064000,
    "full": 1502077189,
    "month": 1501545600,
    "week": 1501977600
  },
  "id": "t3_6s32u3",
  "misc": {
    "postHint": "image"
  },
  "picture": {
    "full": "https://preview.redd.it/uv1q1hk5l8ez.jpg?auto=webp&s=daf1b0e7e50cc17b2a57b657ed95c72fa90d4ed3",
    "preview": "https://preview.redd.it/uv1q1hk5l8ez.jpg?width=640&crop=smart&auto=webp&s=02cb2fe226913b9315d51f7c727e3c9c67e975fc",
    "thumbnail": "https://b.thumbs.redditmedia.com/AfENYjMAXVYcW0bIy2rmF8v2BrhY4-K0LkeIlRK4aqY.jpg"
  },
  "score": {
    "comments": 0,
    "downs": 0,
    "ratio": 0.88,
    "ups": 11,
    "value": 11
  },
  "subreddit": {
    "id": "t5_2sbq3",
    "name": "EarthPorn"
  },
  "tags": [],
  "title": "Antelope Canyon (OC)",
  "url": "https://www.reddit.com/r/EarthPorn/comments/6s32u3/antelope_canyon_1334_x_750oc/"
}
