{
  "author": {
    "id": "t2_a7u2i",
    "name": "Wertson"
  },
  "date": {
    "day": 1420070400,
    "full": 1420150854,
    "month": 1420070400,
    "week": 1419724800
  },
  "id": "t3_2r1idz",
  "misc": {
    "postHint": "image"
  },
  "picture": {
    "full": "https://external-preview.redd.it/enwQXZ2eVTy7shFSAWRbCwQ9ZeHTgg-Zc2Hj_NUirmE.jpg?auto=webp&s=4e994e60ab2be386f42f542ebc4528e69a3c5a96",
    "preview": "https://external-preview.redd.it/enwQXZ2eVTy7shFSAWRbCwQ9ZeHTgg-Zc2Hj_NUirmE.jpg?width=640&crop=smart&auto=webp&s=57ba9630bb18a459f81ed0af7e998208e9670d32",
    "thumbnail": "https://b.thumbs.redditmedia.com/JeylCMdy_5QxJu3lI9bdxhh3tehM89B8_WNuejsW0xc.jpg"
  },
  "score": {
    "comments": 0,
    "downs": 0,
    "ratio": 0.67,
    "ups": 2,
    "value": 2
  },
  "subreddit": {
    "id": "t5_2sbq3",
    "name": "EarthPorn"
  },
  "tags": [],
  "title": "Storm is coming. Rondonia, Brazil.  (OC)",
  "url": "https://www.reddit.com/r/EarthPorn/comments/2r1idz/storm_is_coming_rondonia_brazil_3000x4000_oc/"
}
