{
  "author": {
    "id": "t2_b2nku",
    "name": "slum_baala"
  },
  "date": {
    "day": 1411084800,
    "full": 1411115076,
    "month": 1409529600,
    "week": 1410652800
  },
  "id": "t3_2gueqp",
  "misc": {
    "postHint": "image"
  },
  "picture": {
    "full": "https://external-preview.redd.it/nu01-Q2UvvrhWPeC_WnTfFsiaLoEkIXAJ5vyJvQExAU.jpg?auto=webp&s=949595a3a6e7d9795c7c0eb0335f8f4c283c0c83",
    "preview": "https://external-preview.redd.it/nu01-Q2UvvrhWPeC_WnTfFsiaLoEkIXAJ5vyJvQExAU.jpg?width=640&crop=smart&auto=webp&s=9f2d83604bb2bca7d9334986fcd62590408aabea",
    "thumbnail": "https://a.thumbs.redditmedia.com/dIgyT_HP8vQg1Fl1LOO3KYqMtIPQS8QqaUD3RWKO6v0.jpg"
  },
  "score": {
    "comments": 6,
    "downs": 0,
    "ratio": 0.97,
    "ups": 178,
    "value": 178
  },
  "subreddit": {
    "id": "t5_2sbq3",
    "name": "EarthPorn"
  },
  "tags": [],
  "title": "Mount Baker seen from the Pacific Ocean on a clear summer day, off the Washington coast",
  "url": "https://www.reddit.com/r/EarthPorn/comments/2gueqp/mount_baker_seen_from_the_pacific_ocean_on_a/"
}
