{
  "author": {
    "id": "t2_ox3ypo",
    "name": "Chrome_Tony"
  },
  "date": {
    "day": 1565222400,
    "full": 1565286582,
    "month": 1564617600,
    "week": 1564876800
  },
  "id": "t3_cnp9hb",
  "misc": {
    "postHint": "image"
  },
  "picture": {
    "full": "https://preview.redd.it/5cx8t0h4j9f31.jpg?auto=webp&s=a9a391d32f08bb782fb0b1be4512118cc370b0c8",
    "preview": "https://preview.redd.it/5cx8t0h4j9f31.jpg?width=640&crop=smart&auto=webp&s=2f8d24fe23822ae70d3638db86a733c00a9eb5ba",
    "thumbnail": "https://b.thumbs.redditmedia.com/Zc9_5i5wYAYOWBE7457ZiLiY9gR9R_YkjcIYPCviWpw.jpg"
  },
  "score": {
    "comments": 3,
    "downs": 0,
    "ratio": 0.88,
    "ups": 29,
    "value": 29
  },
  "subreddit": {
    "id": "t5_2sbq3",
    "name": "EarthPorn"
  },
  "tags": [],
  "title": "A perfect day above Bowman Lake in Glacier NP, Montana",
  "url": "https://www.reddit.com/r/EarthPorn/comments/cnp9hb/a_perfect_day_above_bowman_lake_in_glacier_np/"
}
