{
  "author": {
    "id": "t2_keqhi",
    "name": "mattsarge"
  },
  "date": {
    "day": 1485907200,
    "full": 1485955234,
    "month": 1485907200,
    "week": 1485648000
  },
  "id": "t3_5rfeyq",
  "misc": {
    "postHint": "image"
  },
  "picture": {
    "full": "https://preview.redd.it/dhjkl1p1y8dy.jpg?auto=webp&s=832966803b5e134045f2603b8b66374abc49acba",
    "preview": "https://preview.redd.it/dhjkl1p1y8dy.jpg?width=640&crop=smart&auto=webp&s=ce32e610acc00b7978a1832d2603ddcb7be1b60e",
    "thumbnail": "https://a.thumbs.redditmedia.com/xQGh5p2cv1d9Wz0BjqjS0YmzkadxMP5WHuf0lQsAtk4.jpg"
  },
  "score": {
    "comments": 23,
    "downs": 0,
    "ratio": 0.97,
    "ups": 1816,
    "value": 1816
  },
  "subreddit": {
    "id": "t5_2sbq3",
    "name": "EarthPorn"
  },
  "tags": [],
  "title": "Nash Point, South Wales at sunset",
  "url": "https://www.reddit.com/r/EarthPorn/comments/5rfeyq/nash_point_south_wales_at_sunset_oc_1080_x_1350/"
}
