{
  "author": {
    "id": "t2_5jgei",
    "name": "Ken_Thomas"
  },
  "date": {
    "day": 1412553600,
    "full": 1412595689,
    "month": 1412121600,
    "week": 1412467200
  },
  "id": "t3_2ifttd",
  "misc": {
    "postHint": "image"
  },
  "picture": {
    "full": "https://external-preview.redd.it/t_4IzwTqsKGn0JTeQprWhjcjb7l4nnn77CF_OMRrgec.jpg?auto=webp&s=d52379ff97a28d327b29dfff271c9fc84383c4ed",
    "preview": "https://external-preview.redd.it/t_4IzwTqsKGn0JTeQprWhjcjb7l4nnn77CF_OMRrgec.jpg?width=640&crop=smart&auto=webp&s=c0f77cb4c71b2752fe3ae9a70f629812056479c1",
    "thumbnail": "https://b.thumbs.redditmedia.com/i7N1PASvWo4CIixgh9Zw2Yxk9hhfaXx78VExTXsMrnk.jpg"
  },
  "score": {
    "comments": 2,
    "downs": 0,
    "ratio": 0.93,
    "ups": 75,
    "value": 75
  },
  "subreddit": {
    "id": "t5_2sbq3",
    "name": "EarthPorn"
  },
  "tags": [],
  "title": "Early evening, looking out over the Upper Lake from Ladies View - Killarney National Park, Ireland",
  "url": "https://www.reddit.com/r/EarthPorn/comments/2ifttd/early_evening_looking_out_over_the_upper_lake/"
}
