{
  "author": {
    "id": "t2_fzws7",
    "name": "ptrav61"
  },
  "date": {
    "day": 1412640000,
    "full": 1412640022,
    "month": 1412121600,
    "week": 1412467200
  },
  "id": "t3_2ii54z",
  "misc": {
    "postHint": "image"
  },
  "picture": {
    "full": "https://external-preview.redd.it/Sv79deuzaiqO_KZYr3-g2LNCtCtGhKXKV-UrtXk_43s.jpg?auto=webp&s=ed02d924596690562612a3a0064c1516931baf68",
    "preview": "https://external-preview.redd.it/Sv79deuzaiqO_KZYr3-g2LNCtCtGhKXKV-UrtXk_43s.jpg?width=640&crop=smart&auto=webp&s=b685fcd84f25031ca26e60a88188a478c8e0a169",
    "thumbnail": "https://b.thumbs.redditmedia.com/7O-2fKsxcc0kCz29DN1li41iBWfObFPfu_v3XEC2zAQ.jpg"
  },
  "score": {
    "comments": 0,
    "downs": 0,
    "ratio": 1,
    "ups": 3,
    "value": 3
  },
  "subreddit": {
    "id": "t5_2sbq3",
    "name": "EarthPorn"
  },
  "tags": [],
  "title": "Mountains around Marseille in the summer",
  "url": "https://www.reddit.com/r/EarthPorn/comments/2ii54z/mountains_around_marseille_in_the_summer/"
}
