{
  "author": {
    "id": "t2_8r7xc",
    "name": "Beepacker"
  },
  "date": {
    "day": 1386806400,
    "full": 1386878008,
    "month": 1385856000,
    "week": 1386460800
  },
  "id": "t3_1sqmi8",
  "misc": {
    "postHint": "image"
  },
  "picture": {
    "full": "https://external-preview.redd.it/NxuMn_-wWhFIB_uXIOoJhX6X-OBcvOzEvSMr7iIvYGM.jpg?auto=webp&s=ead609474ec04ff8d98e39a6199c5d4446214414",
    "preview": "https://external-preview.redd.it/NxuMn_-wWhFIB_uXIOoJhX6X-OBcvOzEvSMr7iIvYGM.jpg?width=640&crop=smart&auto=webp&s=268187a6c048acf784d9bb11137a502f49ede80e",
    "thumbnail": "https://b.thumbs.redditmedia.com/TT1MPec_YbYV0blLNcw17XOwYzqhy4o4BKuvf4748bk.jpg"
  },
  "score": {
    "comments": 0,
    "downs": 0,
    "ratio": 0.72,
    "ups": 3,
    "value": 3
  },
  "subreddit": {
    "id": "t5_2sbq3",
    "name": "EarthPorn"
  },
  "tags": [],
  "title": "Fingerbowl Lake in the Sierra Nevada Mountain Range in California",
  "url": "https://www.reddit.com/r/EarthPorn/comments/1sqmi8/fingerbowl_lake_in_the_sierra_nevada_mountain/"
}
