{
  "author": {
    "id": "t2_d6wd3",
    "name": "KuramaJinchuriki"
  },
  "date": {
    "day": 1387411200,
    "full": 1387489140,
    "month": 1385856000,
    "week": 1387065600
  },
  "id": "t3_1t9yl0",
  "misc": {
    "postHint": "image"
  },
  "picture": {
    "full": "https://external-preview.redd.it/w2bd94E6B9Kn-AVDf7FHcv8j4yh5_n_FBO3g_qtS34w.jpg?auto=webp&s=e9ecf366ea2ef8dd09e54e04184a23fe764bf3d0",
    "preview": "https://external-preview.redd.it/w2bd94E6B9Kn-AVDf7FHcv8j4yh5_n_FBO3g_qtS34w.jpg?width=640&crop=smart&auto=webp&s=624677029ef6681ff9cc29f7e3e6061edaf3c032",
    "thumbnail": "https://a.thumbs.redditmedia.com/L_dF0JuPo_u61wdbxsxP8wV_IWVum5_UEh2T6hzTJP4.jpg"
  },
  "score": {
    "comments": 3,
    "downs": 0,
    "ratio": 0.84,
    "ups": 53,
    "value": 53
  },
  "subreddit": {
    "id": "t5_2sbq3",
    "name": "EarthPorn"
  },
  "tags": [],
  "title": "Lake Tahoe, California  [2848x4272",
  "url": "https://www.reddit.com/r/EarthPorn/comments/1t9yl0/lake_tahoe_california_oc_2848x4272/"
}
