{
  "author": {
    "id": "t2_3scup",
    "name": "trucidatio"
  },
  "date": {
    "day": 1473033600,
    "full": 1473115819,
    "month": 1472688000,
    "week": 1472947200
  },
  "id": "t3_51c33j",
  "misc": {
    "postHint": "image"
  },
  "picture": {
    "full": "https://preview.redd.it/6327w0jvfsjx.jpg?auto=webp&s=dfc6de256dee0b835eb709a36cfc14fdbfa1f541",
    "preview": "https://preview.redd.it/6327w0jvfsjx.jpg?width=640&crop=smart&auto=webp&s=c072f5c76df82d30cc6e5f7a4deba971c378ac25",
    "thumbnail": "https://b.thumbs.redditmedia.com/FzgFTNvfnGVab2_fVWJ2rdk2QoVsZ1f3vX5Hza7neXs.jpg"
  },
  "score": {
    "comments": 0,
    "downs": 0,
    "ratio": 0.75,
    "ups": 18,
    "value": 18
  },
  "subreddit": {
    "id": "t5_2sbq3",
    "name": "EarthPorn"
  },
  "tags": [],
  "title": "Snow Lake Trail, Wa",
  "url": "https://www.reddit.com/r/EarthPorn/comments/51c33j/snow_lake_trail_wa_oc2988x4254/"
}
