{
  "author": {
    "name": "[deleted]"
  },
  "date": {
    "day": 1309651200,
    "full": 1309665021,
    "month": 1309478400,
    "week": 1309651200
  },
  "id": "t3_iffa5",
  "misc": {
    "postHint": "link"
  },
  "picture": {
    "full": "https://external-preview.redd.it/kSQ4Tcqhw4TzEhABjX8qcxRzO1bmvtKvQDZPpklRKw8.jpg?auto=webp&s=55f75dc96bc028a0ea0dae13686b61463ea47dd1",
    "preview": "https://external-preview.redd.it/kSQ4Tcqhw4TzEhABjX8qcxRzO1bmvtKvQDZPpklRKw8.jpg?width=640&crop=smart&auto=webp&s=c73ca81f87fd31ba9113002b64274b65cc7a120c",
    "thumbnail": "https://a.thumbs.redditmedia.com/vxJCSttG16yDFJ4R483HMqbxKtuuCKptkeEvjn6zH60.jpg"
  },
  "score": {
    "comments": 0,
    "downs": 0,
    "ratio": 0.82,
    "ups": 15,
    "value": 15
  },
  "subreddit": {
    "id": "t5_2sbq3",
    "name": "EarthPorn"
  },
  "tags": [],
  "title": "Coyote Butte, Arizona",
  "url": "https://www.reddit.com/r/EarthPorn/comments/iffa5/coyote_butte_arizona_1024_x_663/"
}
