{
  "author": {
    "id": "t2_bdlhcnj3",
    "name": "curtie_curtt"
  },
  "date": {
    "day": 1625184000,
    "full": 1625264799,
    "month": 1625097600,
    "week": 1624752000
  },
  "id": "t3_ocl23a",
  "misc": {
    "postHint": "image"
  },
  "picture": {
    "full": "https://preview.redd.it/bngwxhu5lv871.jpg?auto=webp&s=ff62657f192962379fd09d062970f8d080064df2",
    "preview": "https://preview.redd.it/bngwxhu5lv871.jpg?width=640&crop=smart&auto=webp&s=bf2e5fb446c4e40a7ae6b8688c87002f8fea04d9",
    "thumbnail": "https://b.thumbs.redditmedia.com/C1pbz_0tykUyserHdpbnAHMGSAtjWAk9gyKGzTZx_xI.jpg"
  },
  "score": {
    "comments": 3,
    "downs": 0,
    "ratio": 0.91,
    "ups": 40,
    "value": 40
  },
  "subreddit": {
    "id": "t5_2sbq3",
    "name": "EarthPorn"
  },
  "tags": [],
  "title": "Bandon State Natural Area, Oregon",
  "url": "https://www.reddit.com/r/EarthPorn/comments/ocl23a/bandon_state_natural_area_oregon_oc_4000x3000/"
}
