{
  "author": {
    "id": "t2_9qldr",
    "name": "opisska"
  },
  "date": {
    "day": 1601424000,
    "full": 1601487574,
    "month": 1598918400,
    "week": 1601164800
  },
  "id": "t3_j2qtgi",
  "misc": {
    "postHint": "image"
  },
  "picture": {
    "full": "https://preview.redd.it/5jgazye4nbq51.jpg?auto=webp&s=ae6fe6f1afaba772ff68a921f86ab38404de0a4f",
    "preview": "https://preview.redd.it/5jgazye4nbq51.jpg?width=640&crop=smart&auto=webp&s=6612b2a000646dd435f1550eaba9bf2ef281e7e5",
    "thumbnail": "https://a.thumbs.redditmedia.com/XnD6MTIiZ9naYIpSKOn_kBh4XrN0OvVJWHA7H6u1Su8.jpg"
  },
  "score": {
    "comments": 10,
    "downs": 0,
    "ratio": 0.98,
    "ups": 73,
    "value": 73
  },
  "subreddit": {
    "id": "t5_2sbq3",
    "name": "EarthPorn"
  },
  "tags": [],
  "title": "A less known corner of Wadi Rum, Jordan",
  "url": "https://www.reddit.com/r/EarthPorn/comments/j2qtgi/a_less_known_corner_of_wadi_rum_jordan_3487x1963/"
}
