{
  "author": {
    "id": "t2_gmsci",
    "name": "Pflunt"
  },
  "date": {
    "day": 1545868800,
    "full": 1545935680,
    "month": 1543622400,
    "week": 1545523200
  },
  "id": "t3_aa1sb0",
  "misc": {
    "postHint": "image"
  },
  "picture": {
    "full": "https://preview.redd.it/497mihsn6v621.jpg?auto=webp&s=05152e0d5324e0ddf9008ae1e983bc30562f2028",
    "preview": "https://preview.redd.it/497mihsn6v621.jpg?width=640&crop=smart&auto=webp&s=bc50091c0823c1edddd774831e40e694b4fbda89",
    "thumbnail": "https://b.thumbs.redditmedia.com/cRZ_Do6xSM_FLKV8WRzlbMpLnpdQ3Z3BaShRWazph8I.jpg"
  },
  "score": {
    "comments": 11,
    "downs": 0,
    "ratio": 0.98,
    "ups": 705,
    "value": 705
  },
  "subreddit": {
    "id": "t5_2sbq3",
    "name": "EarthPorn"
  },
  "tags": [],
  "title": "Just a few of the highly improbable geological formations found in the Fairy Tale Canyon of Northeast Kyrgyzstan. More in Comments!",
  "url": "https://www.reddit.com/r/EarthPorn/comments/aa1sb0/just_a_few_of_the_highly_improbable_geological/"
}
