{
  "author": {
    "id": "t2_5vgl2smw",
    "name": "Robert_Killar"
  },
  "date": {
    "day": 1588204800,
    "full": 1588266308,
    "month": 1585699200,
    "week": 1587859200
  },
  "id": "t3_gazo19",
  "misc": {
    "postHint": "image"
  },
  "picture": {
    "full": "https://preview.redd.it/qboxmsmflzv41.jpg?auto=webp&s=6ae1294ff8ee971df51e897766d914a8fdec9dd1",
    "preview": "https://preview.redd.it/qboxmsmflzv41.jpg?width=640&crop=smart&auto=webp&s=1180940122aa86ef9ac999671e34f0fe7804c68f",
    "thumbnail": "https://b.thumbs.redditmedia.com/RVZwwXBmoSY-bKb9Bv5xUwNu_CLeaHEPrFj-X9IBfkM.jpg"
  },
  "score": {
    "comments": 0,
    "downs": 0,
    "ratio": 0.86,
    "ups": 19,
    "value": 19
  },
  "subreddit": {
    "id": "t5_2sbq3",
    "name": "EarthPorn"
  },
  "tags": [],
  "title": "Juniper trees. Estonia, Saaremaa",
  "url": "https://www.reddit.com/r/EarthPorn/comments/gazo19/juniper_trees_estonia_saaremaa_oc_51843456/"
}
