{
  "author": {
    "name": "[deleted]"
  },
  "date": {
    "day": 1588550400,
    "full": 1588600335,
    "month": 1588291200,
    "week": 1588464000
  },
  "id": "t3_gdbznf",
  "misc": {
    "postHint": "image"
  },
  "picture": {
    "full": "https://preview.redd.it/shvt86nl6rw41.jpg?auto=webp&s=a5b84a688c9fc31835aba8a3ef901f4659d69948",
    "preview": "https://preview.redd.it/shvt86nl6rw41.jpg?width=640&crop=smart&auto=webp&s=c5ede2c573429b45d990bf90f4c54dad203004e6",
    "thumbnail": "https://b.thumbs.redditmedia.com/wxO29xnta1Sp4V-npLh_z8wQZ6d3WcYuXRrJABYl2yM.jpg"
  },
  "score": {
    "comments": 0,
    "downs": 0,
    "ratio": 0.82,
    "ups": 27,
    "value": 27
  },
  "subreddit": {
    "id": "t5_2sbq3",
    "name": "EarthPorn"
  },
  "tags": [],
  "title": "Natural Pool at Diyaluma Falls, Koslanda, Sri Lanka,",
  "url": "https://www.reddit.com/r/EarthPorn/comments/gdbznf/natural_pool_at_diyaluma_falls_koslanda_sri_lanka/"
}
