{
  "author": {
    "id": "t2_l49h4",
    "name": "SmashedWand1035"
  },
  "date": {
    "day": 1590883200,
    "full": 1590915536,
    "month": 1588291200,
    "week": 1590883200
  },
  "id": "t3_gtvpvv",
  "misc": {
    "postHint": "image"
  },
  "picture": {
    "full": "https://preview.redd.it/klgg2066f2251.jpg?auto=webp&s=fa2dee2c9397008644d525438d14bdfc0448208f",
    "preview": "https://preview.redd.it/klgg2066f2251.jpg?width=640&crop=smart&auto=webp&s=b034449815c924b1d31fd82e2574ea060a51a734",
    "thumbnail": "https://a.thumbs.redditmedia.com/eKLPDR28T2XHUDYhJ5bfXCtLfHhHxAzNOpI8JEH0CI4.jpg"
  },
  "score": {
    "comments": 3,
    "downs": 0,
    "ratio": 0.97,
    "ups": 281,
    "value": 281
  },
  "subreddit": {
    "id": "t5_2sbq3",
    "name": "EarthPorn"
  },
  "tags": [],
  "title": "Wanaka, NZ",
  "url": "https://www.reddit.com/r/EarthPorn/comments/gtvpvv/wanaka_nz_oc_3862x2431/"
}
