{
  "author": {
    "id": "t2_paffy",
    "name": "theodolus"
  },
  "date": {
    "day": 1485475200,
    "full": 1485561004,
    "month": 1483228800,
    "week": 1485043200
  },
  "id": "t3_5qkm87",
  "misc": {
    "postHint": "image"
  },
  "picture": {
    "full": "https://preview.redd.it/avh7exymdccy.jpg?auto=webp&s=b1577ca8f47b90d7eefd79dc5843b8c7179b85f0",
    "preview": "https://preview.redd.it/avh7exymdccy.jpg?width=640&crop=smart&auto=webp&s=c3a42d8cea4d51700c44cd5c55e558b5777cacd5",
    "thumbnail": "https://b.thumbs.redditmedia.com/0DQL1evVbOMuXJfN4rzPxdqpSPLj7PshqCtn_RVQ5tw.jpg"
  },
  "score": {
    "comments": 0,
    "downs": 0,
    "ratio": 0.88,
    "ups": 20,
    "value": 20
  },
  "subreddit": {
    "id": "t5_2sbq3",
    "name": "EarthPorn"
  },
  "tags": [],
  "title": "Nisqually River at Longmire, WA by Theodolus (OC)  taken with a MotoZForce",
  "url": "https://www.reddit.com/r/EarthPorn/comments/5qkm87/nisqually_river_at_longmire_wa_by_theodolus_oc/"
}
