{
  "author": {
    "id": "t2_16ktgq",
    "name": "Athy00"
  },
  "date": {
    "day": 1559174400,
    "full": 1559199613,
    "month": 1556668800,
    "week": 1558828800
  },
  "id": "t3_buq23t",
  "misc": {
    "postHint": "image"
  },
  "picture": {
    "full": "https://preview.redd.it/rx5dk0ufra131.jpg?auto=webp&s=99879b85e8ec7a8ba27b9e356643ae4d8e2e090c",
    "preview": "https://preview.redd.it/rx5dk0ufra131.jpg?width=640&crop=smart&auto=webp&s=d3fcaae413eb7d97af8ba189891bb9fbbe2d3ce1",
    "thumbnail": "https://b.thumbs.redditmedia.com/jVOpkN3njL24gIGvCAJ8KmHEjiCGpW1VLlXNU9ycvOY.jpg"
  },
  "score": {
    "comments": 8,
    "downs": 0,
    "ratio": 0.97,
    "ups": 494,
    "value": 494
  },
  "subreddit": {
    "id": "t5_2sbq3",
    "name": "EarthPorn"
  },
  "tags": [],
  "title": "Bluebells! - Dockey Wood, Chilterns",
  "url": "https://www.reddit.com/r/EarthPorn/comments/buq23t/bluebells_dockey_wood_chilterns_oc_5312x2988/"
}
