{
  "author": {
    "id": "t2_qsobjhh",
    "name": "euphoricash"
  },
  "date": {
    "day": 1515110400,
    "full": 1515132871,
    "month": 1514764800,
    "week": 1514678400
  },
  "id": "t3_7o9btl",
  "misc": {
    "postHint": "image"
  },
  "picture": {
    "full": "https://preview.redd.it/vk0bjuuby6801.jpg?auto=webp&s=4209652315cee525a9c4181c0e7fae1c21b9c13c",
    "preview": "https://preview.redd.it/vk0bjuuby6801.jpg?width=640&crop=smart&auto=webp&s=a636b48a64b84f9dd7a05e979be14ea77327f008",
    "thumbnail": "https://b.thumbs.redditmedia.com/-sOAkD1rVH5KO8RtXRlK0tR-wwJQH0srpYQ8tqqViwk.jpg"
  },
  "score": {
    "comments": 1,
    "downs": 0,
    "ratio": 0.84,
    "ups": 19,
    "value": 19
  },
  "subreddit": {
    "id": "t5_2sbq3",
    "name": "EarthPorn"
  },
  "tags": ["[3264x2448]"],
  "title": "Mammoth hot springs",
  "url": "https://www.reddit.com/r/EarthPorn/comments/7o9btl/mammoth_hot_springs_oc1136x640/"
}
