{
  "author": {
    "id": "t2_eo2xr",
    "name": "jeckertphoto"
  },
  "date": {
    "day": 1390348800,
    "full": 1390355096,
    "month": 1388534400,
    "week": 1390089600
  },
  "id": "t3_1vtblj",
  "misc": {
    "postHint": "link"
  },
  "picture": {
    "full": "https://external-preview.redd.it/yYfsDATAuUHqJUK7lMcSlSdLrmy5Pd0s2FqLvIzwUEU.jpg?auto=webp&s=413cccb12c59c2eb8ce4f30f57939a23c4717403",
    "preview": "https://external-preview.redd.it/yYfsDATAuUHqJUK7lMcSlSdLrmy5Pd0s2FqLvIzwUEU.jpg?width=640&crop=smart&auto=webp&s=b44ee81f6c60306f28d353944446f641746431cf",
    "thumbnail": "https://b.thumbs.redditmedia.com/EAP6jKkUuaNOyRfHcCro92y1nMO6OU1QkiEUlPNEMSk.jpg"
  },
  "score": {
    "comments": 0,
    "downs": 0,
    "ratio": 0.67,
    "ups": 2,
    "value": 2
  },
  "subreddit": {
    "id": "t5_2sbq3",
    "name": "EarthPorn"
  },
  "tags": [],
  "title": "Ozark Branches - Ozarks, Arkansas, USA",
  "url": "https://www.reddit.com/r/EarthPorn/comments/1vtblj/ozark_branches_ozarks_arkansas_usa_1280x854_oc/"
}
