{
  "author": {
    "id": "t2_o0fz2",
    "name": "duttyRI"
  },
  "date": {
    "day": 1447027200,
    "full": 1447081213,
    "month": 1446336000,
    "week": 1446940800
  },
  "id": "t3_3s50z1",
  "misc": {
    "postHint": "image"
  },
  "picture": {
    "full": "https://external-preview.redd.it/dg3WTwbMEIejqH9VaMricMNl4M2hp3RVjLtvDkKS7KA.jpg?auto=webp&s=6b0747ea9e282c0889fa72d494033d90acf8ef7f",
    "preview": "https://external-preview.redd.it/dg3WTwbMEIejqH9VaMricMNl4M2hp3RVjLtvDkKS7KA.jpg?width=640&crop=smart&auto=webp&s=1653a68371226e95114eba13178f056e01488aaf",
    "thumbnail": "https://b.thumbs.redditmedia.com/M-yfH9AWq94TPmCDBK7D0Hsc9f8D38ADKdSVNHAv0KE.jpg"
  },
  "score": {
    "comments": 0,
    "downs": 0,
    "ratio": 0.88,
    "ups": 6,
    "value": 6
  },
  "subreddit": {
    "id": "t5_2sbq3",
    "name": "EarthPorn"
  },
  "tags": [],
  "title": "A few more minutes and I would've completely 'mist' this shot in Vermont!",
  "url": "https://www.reddit.com/r/EarthPorn/comments/3s50z1/a_few_more_minutes_and_i_wouldve_completely_mist/"
}
