{
  "author": {
    "id": "t2_16kjg3",
    "name": "jonjon1969"
  },
  "date": {
    "day": 1491177600,
    "full": 1491180738,
    "month": 1491004800,
    "week": 1491091200
  },
  "id": "t3_633ie4",
  "misc": {
    "postHint": "link"
  },
  "picture": {
    "full": "https://external-preview.redd.it/C_tRj1mzK46HAqf99E0V1MbSZQI0dDi6JUqtza5qi8M.jpg?auto=webp&s=e5e9b3a7b01de303709cd656b7643fbad2dc7796",
    "preview": "https://external-preview.redd.it/C_tRj1mzK46HAqf99E0V1MbSZQI0dDi6JUqtza5qi8M.jpg?width=640&crop=smart&auto=webp&s=752dff0359796204ff5a41a7d6eb0ed0abf1b861",
    "thumbnail": "https://b.thumbs.redditmedia.com/pP00uV3boZmHf_N3YGTNnSJqJDzlhbo4-_3KBKP6TjY.jpg"
  },
  "score": {
    "comments": 1,
    "downs": 0,
    "ratio": 0.79,
    "ups": 10,
    "value": 10
  },
  "subreddit": {
    "id": "t5_2sbq3",
    "name": "EarthPorn"
  },
  "tags": [],
  "title": "Creek that makes its way to two waterfalls in Montezuma Costa Rica",
  "url": "https://www.reddit.com/r/EarthPorn/comments/633ie4/8521136_oc_creek_that_makes_its_way_to_two/"
}
