{
  "author": {
    "id": "t2_4mt7q",
    "name": "Mind_Virus"
  },
  "date": {
    "day": 1336867200,
    "full": 1336928866,
    "month": 1335830400,
    "week": 1336867200
  },
  "id": "t3_tl58o",
  "misc": {
    "postHint": "image"
  },
  "picture": {
    "full": "https://external-preview.redd.it/FGWIui13ZAcC0seFm37UDjj8rHXW9W2p4yu8gl3ntDo.jpg?auto=webp&s=6fadb9c9cab036a2b7ec8a64dc513149b6d3b90f",
    "preview": "https://external-preview.redd.it/FGWIui13ZAcC0seFm37UDjj8rHXW9W2p4yu8gl3ntDo.jpg?width=640&crop=smart&auto=webp&s=cad0e623fceff3e0b06e2b59863d828780d42167",
    "thumbnail": "https://b.thumbs.redditmedia.com/mA2Rgs-JGJTboj06mdBFf3-hkTSG4yGItdjruqAv_zg.jpg"
  },
  "score": {
    "comments": 19,
    "downs": 0,
    "ratio": 0.92,
    "ups": 1064,
    "value": 1064
  },
  "subreddit": {
    "id": "t5_2sbq3",
    "name": "EarthPorn"
  },
  "tags": [],
  "title": "Whims of the winter river - Location unknown",
  "url": "https://www.reddit.com/r/EarthPorn/comments/tl58o/whims_of_the_winter_river_location_unknown_900x658/"
}
