{
  "author": {
    "id": "t2_21x08vkb",
    "name": "jwsm13"
  },
  "date": {
    "day": 1551398400,
    "full": 1551411495,
    "month": 1551398400,
    "week": 1550966400
  },
  "id": "t3_aw02ou",
  "misc": {
    "postHint": "image"
  },
  "picture": {
    "full": "https://preview.redd.it/90pyyy68hfj21.jpg?auto=webp&s=383a27d5652d83ab22033a86d0e745061c79c52c",
    "preview": "https://preview.redd.it/90pyyy68hfj21.jpg?width=640&crop=smart&auto=webp&s=e424998af0f800f55690fee2cca091c3c458b2fb",
    "thumbnail": "https://b.thumbs.redditmedia.com/5rYWZj9DHv7QZdzOYi_2klE409IaFgUqFhGwT_YQYuo.jpg"
  },
  "score": {
    "comments": 0,
    "downs": 0,
    "ratio": 0.67,
    "ups": 7,
    "value": 7
  },
  "subreddit": {
    "id": "t5_2sbq3",
    "name": "EarthPorn"
  },
  "tags": [],
  "title": "Near a ski slope, Otaru, Hokkaido, Japan",
  "url": "https://www.reddit.com/r/EarthPorn/comments/aw02ou/near_a_ski_slope_otaru_hokkaido_japan_oc_4640_x/"
}
