{
  "author": {
    "id": "t2_ict8c",
    "name": "Das_a_good_seagull"
  },
  "date": {
    "day": 1489881600,
    "full": 1489902470,
    "month": 1488326400,
    "week": 1489881600
  },
  "id": "t3_608pqi",
  "misc": {
    "postHint": "image"
  },
  "picture": {
    "full": "https://external-preview.redd.it/dMeFg0eEUXm54RvIng1r4hk1sTOelFqMTxrCPPydBqg.jpg?auto=webp&s=8c54030b4adbe4c24fdd3feddec8426623d56111",
    "preview": "https://external-preview.redd.it/dMeFg0eEUXm54RvIng1r4hk1sTOelFqMTxrCPPydBqg.jpg?width=640&crop=smart&auto=webp&s=c67fafcf8e62289030ba8ffbe2389f65fb137ec4",
    "thumbnail": "https://b.thumbs.redditmedia.com/Qv5pLiS19K0M77V9eGm_8VjweLwjS-hxf9ZA-jEDDUQ.jpg"
  },
  "score": {
    "comments": 5,
    "downs": 0,
    "ratio": 0.81,
    "ups": 16,
    "value": 16
  },
  "subreddit": {
    "id": "t5_2sbq3",
    "name": "EarthPorn"
  },
  "tags": [],
  "title": "Castle Rock State Park (OC)",
  "url": "https://www.reddit.com/r/EarthPorn/comments/608pqi/castle_rock_state_park_oc_5312x2988/"
}
