{
  "author": {
    "id": "t2_fz2p0",
    "name": "knightrider10"
  },
  "date": {
    "day": 1490486400,
    "full": 1490541740,
    "month": 1488326400,
    "week": 1490486400
  },
  "id": "t3_61m28n",
  "misc": {
    "postHint": "image"
  },
  "picture": {
    "full": "https://preview.redd.it/mal3mdr4srny.jpg?auto=webp&s=f7e29cc02164428848032362a7c70cf611828601",
    "preview": "https://preview.redd.it/mal3mdr4srny.jpg?width=640&crop=smart&auto=webp&s=8abbf994a988719fcdcea1c5fbea9841c75d8502",
    "thumbnail": "https://a.thumbs.redditmedia.com/9IOUhFpnsZy5Svmoi8lBHnTC4JrJimeMgTWuh3v2Ah4.jpg"
  },
  "score": {
    "comments": 1,
    "downs": 0,
    "ratio": 0.96,
    "ups": 17,
    "value": 17
  },
  "subreddit": {
    "id": "t5_2sbq3",
    "name": "EarthPorn"
  },
  "tags": [],
  "title": "Waimea Canyon State Park, Kauai",
  "url": "https://www.reddit.com/r/EarthPorn/comments/61m28n/waimea_canyon_state_park_kauai_oc_3888_2593/"
}
