{
  "author": {
    "id": "t2_3v25s",
    "name": "AHWagner"
  },
  "date": {
    "day": 1394409600,
    "full": 1394419036,
    "month": 1393632000,
    "week": 1394323200
  },
  "id": "t3_200ldl",
  "misc": {
    "postHint": "link"
  },
  "picture": {
    "full": "https://external-preview.redd.it/mXA0HzObNRRybtHQZcq6PkNm4K70StjmGO7_RTUgr50.jpg?auto=webp&s=2b2aa697e44a0061affc6e8eaf4651ffb1b2b9bb",
    "preview": "https://external-preview.redd.it/mXA0HzObNRRybtHQZcq6PkNm4K70StjmGO7_RTUgr50.jpg?width=640&crop=smart&auto=webp&s=cc0351423e8af845d5a337a4bf280580733deb72",
    "thumbnail": "https://a.thumbs.redditmedia.com/kfOlevoj3CC5sLcsnMpMmx90sS_6ZymSTbZceD69OO8.jpg"
  },
  "score": {
    "comments": 3,
    "downs": 0,
    "ratio": 0.91,
    "ups": 17,
    "value": 17
  },
  "subreddit": {
    "id": "t5_2sbq3",
    "name": "EarthPorn"
  },
  "tags": [],
  "title": "A Maryland Snowscape",
  "url": "https://www.reddit.com/r/EarthPorn/comments/200ldl/a_maryland_snowscape_oc_2048x684/"
}
