{
  "author": {
    "id": "t2_14f1x9",
    "name": "Mardzi10"
  },
  "date": {
    "day": 1563148800,
    "full": 1563189508,
    "month": 1561939200,
    "week": 1563062400
  },
  "id": "t3_cdg73r",
  "misc": {
    "postHint": "link"
  },
  "picture": {
    "full": "https://external-preview.redd.it/3VJCAevkQHIjn1peDr-MMd55r2g2_SWS8lKtX2mr-eo.jpg?auto=webp&s=e6a059916b234004b3932aa431549f4f6569b411",
    "preview": "https://external-preview.redd.it/3VJCAevkQHIjn1peDr-MMd55r2g2_SWS8lKtX2mr-eo.jpg?width=640&crop=smart&auto=webp&s=563c32622d22ff439d5f5a5444a1fa98dcc784cb",
    "thumbnail": "https://b.thumbs.redditmedia.com/adRO4xX70auLZoD-lNgxFJxCHgz66Z7wutAFd4nL5dQ.jpg"
  },
  "score": {
    "comments": 0,
    "downs": 0,
    "ratio": 0.86,
    "ups": 29,
    "value": 29
  },
  "subreddit": {
    "id": "t5_2sbq3",
    "name": "EarthPorn"
  },
  "tags": [],
  "title": "Stołowe Mountains National Park, Poland",
  "url": "https://www.reddit.com/r/EarthPorn/comments/cdg73r/stołowe_mountains_national_park_poland_oc/"
}
