{
  "author": {
    "id": "t2_drbee",
    "name": "Tankus44"
  },
  "date": {
    "day": 1464912000,
    "full": 1464988883,
    "month": 1464739200,
    "week": 1464480000
  },
  "id": "t3_4mf4oa",
  "misc": {
    "postHint": "link"
  },
  "picture": {
    "full": "https://external-preview.redd.it/tTXE2OyCixFrtqXJMy-eIgQErD5oVe20-wUUEbuQNeM.jpg?auto=webp&s=cc927c36d2542e8ef98abe559ee4ab5e1f779c40",
    "preview": "https://external-preview.redd.it/tTXE2OyCixFrtqXJMy-eIgQErD5oVe20-wUUEbuQNeM.jpg?width=640&crop=smart&auto=webp&s=b9c26b6764c235bcb29a0530e278b3db7f2e9c83",
    "thumbnail": "https://b.thumbs.redditmedia.com/kl8D85ZGYOcNncpNSKCSf4cQ-0FQluMDXYSWHbi8GGc.jpg"
  },
  "score": {
    "comments": 21,
    "downs": 0,
    "ratio": 0.93,
    "ups": 794,
    "value": 794
  },
  "subreddit": {
    "id": "t5_2sbq3",
    "name": "EarthPorn"
  },
  "tags": [],
  "title": "Just returned from my annual trip to Yosemite and it still takes leaves me speechless.  OC",
  "url": "https://www.reddit.com/r/EarthPorn/comments/4mf4oa/just_returned_from_my_annual_trip_to_yosemite_and/"
}
