{
  "author": {
    "id": "t2_d4w1s",
    "name": "HankHil"
  },
  "date": {
    "day": 1478304000,
    "full": 1478375814,
    "month": 1477958400,
    "week": 1477785600
  },
  "id": "t3_5bbsvl",
  "misc": {
    "postHint": "image"
  },
  "picture": {
    "full": "https://preview.redd.it/tqbp35kqwuvx.jpg?auto=webp&s=7f27c8bd86a7178367ad729e70725469b3c21814",
    "preview": "https://preview.redd.it/tqbp35kqwuvx.jpg?width=640&crop=smart&auto=webp&s=c9034eadd3810794064dc301b15335196c0a3d06",
    "thumbnail": "https://b.thumbs.redditmedia.com/RC_jRkt3SCcQoIL7D3XQAQ-Th6ZN7S2qNFI6AaicN8E.jpg"
  },
  "score": {
    "comments": 1,
    "downs": 0,
    "ratio": 0.7,
    "ups": 16,
    "value": 16
  },
  "subreddit": {
    "id": "t5_2sbq3",
    "name": "EarthPorn"
  },
  "tags": ["Probable OC - feedback needed from OP"],
  "title": "Southcoast of Als - Denmark",
  "url": "https://www.reddit.com/r/EarthPorn/comments/5bbsvl/southcoast_of_als_denmark_1752_3120/"
}
