{
  "author": {
    "id": "t2_xco0p",
    "name": "BryanPenfound"
  },
  "date": {
    "day": 1528934400,
    "full": 1528942543,
    "month": 1527811200,
    "week": 1528588800
  },
  "id": "t3_8qy74v",
  "misc": {
    "postHint": "image"
  },
  "picture": {
    "full": "https://preview.redd.it/q00n60sklv311.jpg?auto=webp&s=69a5e1a966b3a31af88f06d19e2136231f6208f5",
    "preview": "https://preview.redd.it/q00n60sklv311.jpg?width=640&crop=smart&auto=webp&s=c5c2a58355046142b2db27d87d387b760639a226",
    "thumbnail": "https://b.thumbs.redditmedia.com/vsvHqdMszgZkLa8yjlokoAQCQzsfQPkMveVZG5HAsfU.jpg"
  },
  "score": {
    "comments": 0,
    "downs": 0,
    "ratio": 0.94,
    "ups": 64,
    "value": 64
  },
  "subreddit": {
    "id": "t5_2sbq3",
    "name": "EarthPorn"
  },
  "tags": [],
  "title": "Coquihalla Canyon Provincial Park, Hope, BC, Canada",
  "url": "https://www.reddit.com/r/EarthPorn/comments/8qy74v/coquihalla_canyon_provincial_park_hope_bc_canada/"
}
