{
  "author": {
    "id": "t2_8289y",
    "name": "joeh4384"
  },
  "date": {
    "day": 1527811200,
    "full": 1527812716,
    "month": 1527811200,
    "week": 1527379200
  },
  "id": "t3_8nniwn",
  "misc": {
    "postHint": "image"
  },
  "picture": {
    "full": "https://preview.redd.it/4af3a62y9a111.jpg?auto=webp&s=ca547762200cdea0b515da12e82add82b2988112",
    "preview": "https://preview.redd.it/4af3a62y9a111.jpg?width=640&crop=smart&auto=webp&s=0556dc021e2fe4c18b88788212355456b2472376",
    "thumbnail": "https://a.thumbs.redditmedia.com/pG72Y2geJVI3UGMvHaTeueCpQQAIsV8g7nLmMgisOb0.jpg"
  },
  "score": {
    "comments": 0,
    "downs": 0,
    "ratio": 0.93,
    "ups": 11,
    "value": 11
  },
  "subreddit": {
    "id": "t5_2sbq3",
    "name": "EarthPorn"
  },
  "tags": [],
  "title": "Foggy Flowerpot Island, Tobermory, ON CA",
  "url": "https://www.reddit.com/r/EarthPorn/comments/8nniwn/foggy_flowerpot_island_tobermory_on_ca_oc6000_x/"
}
